aliyunsdkresourcecenter/__init__.py
aliyunsdkresourcecenter/request/__init__.py
aliyunsdkresourcecenter/request/v20221201/AssociateDefaultFilterRequest.py
aliyunsdkresourcecenter/request/v20221201/CreateDeliveryChannelRequest.py
aliyunsdkresourcecenter/request/v20221201/CreateFilterRequest.py
aliyunsdkresourcecenter/request/v20221201/CreateMultiAccountDeliveryChannelRequest.py
aliyunsdkresourcecenter/request/v20221201/CreateSavedQueryRequest.py
aliyunsdkresourcecenter/request/v20221201/DeleteDeliveryChannelRequest.py
aliyunsdkresourcecenter/request/v20221201/DeleteFilterRequest.py
aliyunsdkresourcecenter/request/v20221201/DeleteMultiAccountDeliveryChannelRequest.py
aliyunsdkresourcecenter/request/v20221201/DeleteSavedQueryRequest.py
aliyunsdkresourcecenter/request/v20221201/DisableMultiAccountResourceCenterRequest.py
aliyunsdkresourcecenter/request/v20221201/DisableResourceCenterRequest.py
aliyunsdkresourcecenter/request/v20221201/DisassociateDefaultFilterRequest.py
aliyunsdkresourcecenter/request/v20221201/EnableMultiAccountResourceCenterRequest.py
aliyunsdkresourcecenter/request/v20221201/EnableResourceCenterRequest.py
aliyunsdkresourcecenter/request/v20221201/ExecuteMultiAccountSQLQueryRequest.py
aliyunsdkresourcecenter/request/v20221201/ExecuteSQLQueryRequest.py
aliyunsdkresourcecenter/request/v20221201/GetDeliveryChannelRequest.py
aliyunsdkresourcecenter/request/v20221201/GetDeliveryChannelStatisticsRequest.py
aliyunsdkresourcecenter/request/v20221201/GetExampleQueryRequest.py
aliyunsdkresourcecenter/request/v20221201/GetMultiAccountDeliveryChannelRequest.py
aliyunsdkresourcecenter/request/v20221201/GetMultiAccountDeliveryChannelStatisticsRequest.py
aliyunsdkresourcecenter/request/v20221201/GetMultiAccountResourceCenterServiceStatusRequest.py
aliyunsdkresourcecenter/request/v20221201/GetMultiAccountResourceConfigurationRequest.py
aliyunsdkresourcecenter/request/v20221201/GetResourceCenterServiceStatusRequest.py
aliyun_python_sdk_resourcecenter-1.0.7.dist-info/LICENSE
aliyun_python_sdk_resourcecenter-1.0.7.dist-info/METADATA
aliyun_python_sdk_resourcecenter-1.0.7.dist-info/WHEEL
aliyun_python_sdk_resourcecenter-1.0.7.dist-info/top_level.txt
aliyun_python_sdk_resourcecenter-1.0.7.dist-info/RECORD
